{
	"apiVersion": 3,
	"name": "dp/soc-share",
	"title": "DP Social Share",
	"category": "design",
	"description": "DP Social Share block",
	"textdomain": "default",
	"attributes": {
		"icoMarginRight": {
			"type": "string",
			"default": "4"
		},
		"icoHeight": {
			"type": "string",
			"default": "24"
		},
		"icoColor": {
			"type": "string",
			"default": "grey"
		},
		"icoColorHover": {
			"type": "string",
			"default": "black"
		}
	},
	"supports": {
		"anchor": true,
		"align": true,
		"html": true
	},
	"editorScript": "file:./index.js",
	"editorStyle": "file:./index.css"
}